MANIFEST.in
README.txt
setup.cfg
setup.py
docs/HISTORY.txt
horae/__init__.py
horae.properties.egg-info/PKG-INFO
horae.properties.egg-info/SOURCES.txt
horae.properties.egg-info/dependency_links.txt
horae.properties.egg-info/entry_points.txt
horae.properties.egg-info/namespace_packages.txt
horae.properties.egg-info/not-zip-safe
horae.properties.egg-info/requires.txt
horae.properties.egg-info/top_level.txt
horae/properties/__init__.py
horae/properties/configuration.py
horae/properties/configure.zcml
horae/properties/interfaces.py
horae/properties/overrides.zcml
horae/properties/propertied.py
horae/properties/properties.py
horae/properties/views.py
horae/properties/vocabulary.py
horae/properties/widgets.py
horae/properties/locales/horae.properties.pot
horae/properties/locales/de/LC_MESSAGES/horae.properties.mo
horae/properties/locales/de/LC_MESSAGES/horae.properties.po
horae/properties/templates/history.cpt
horae/properties/templates/properties.cpt
horae/properties/templates/propertiesoverview.cpt